API-Kit/__init__.py
API-Kit/main.py
pythonapikit/__init__.py
pythonapikit/main.py
pythonapikit-0.0.3.dist-info/METADATA
pythonapikit-0.0.3.dist-info/WHEEL
pythonapikit-0.0.3.dist-info/top_level.txt
pythonapikit-0.0.3.dist-info/RECORD
