Metadata-Version: 2.1
Name: pythonapikit
Version: 0.0.3
Summary: Collection of different APIs.
Author: ShadowFlameFox
Author-email: <shadow_flame_fox@web.de>
Keywords: Python,API,Weather,Collection,Integration,Wrapper,Client,Request,Endpoint,HTTP,REST,Web Services,Connector,Utility,Toolset,Helper,Manager,Facade,Handler,Assist,Bundle,Kit,JSON
Classifier: Development Status :: 1 - Planning
Classifier: Intended Audience :: Developers
Classifier: Programming Language :: Python :: 3.11
Classifier: Operating System :: Unix
Classifier: Operating System :: MacOS :: MacOS X
Classifier: Operating System :: Microsoft :: Windows
Requires-Dist: requests
